ZerZ_test-0.0.1.dist-info/METADATA
ZerZ_test-0.0.1.dist-info/RECORD
ZerZ_test-0.0.1.dist-info/WHEEL
ZerZ_test-0.0.1.dist-info/top_level.txt
test_pkg/__init__.py
