Metadata-Version: 2.1
Name: ZerZ-test
Version: 0.0.1
Summary: A sma;; exmaple package
Home-page: https://github.com/pypa/example-project
Author: Example Author
Author-email: author@example.com
License: UNKNOWN
Platform: UNKNOWN
